dead_simple_framework/__init__.py
dead_simple_framework/encoder.py
dead_simple_framework/jwt.py
dead_simple_framework/main.py
dead_simple_framework/router.py
dead_simple_framework/slack.py
dead_simple_framework/api/__init__.py
dead_simple_framework/api/client.py
dead_simple_framework/api/errors.py
dead_simple_framework/api/main.py
dead_simple_framework/api/utils.py
dead_simple_framework/cache/__init__.py
dead_simple_framework/cache/main.py
dead_simple_framework/config/__init__.py
dead_simple_framework/config/config.py
dead_simple_framework/config/route.py
dead_simple_framework/config/schema.py
dead_simple_framework/config/task.py
dead_simple_framework/config/settings/__init__.py
dead_simple_framework/config/settings/app_settings.py
dead_simple_framework/config/settings/jwt_settings.py
dead_simple_framework/config/settings/main.py
dead_simple_framework/config/settings/mongodb_settings.py
dead_simple_framework/config/settings/rabbitmq_settings.py
dead_simple_framework/config/settings/redis_settings.py
dead_simple_framework/config/settings/sentry_settings.py
dead_simple_framework/config/settings/setting.py
dead_simple_framework/config/settings/slack_settings.py
dead_simple_framework/database/__init__.py
dead_simple_framework/database/fixtures.py
dead_simple_framework/database/index.py
dead_simple_framework/database/main.py
dead_simple_framework/database/utils.py
dead_simple_framework/handlers/__init__.py
dead_simple_framework/handlers/default.py
dead_simple_framework/handlers/login.py
dead_simple_framework/handlers/permissions.py
dead_simple_framework/handlers/users.py
dead_simple_framework/tasks/__init__.py
dead_simple_framework/tasks/main.py
dead_simple_framework/tasks/task.py
dead_simple_framework/tasks/utils.py
dead_simple_framework-1.3.9.dist-info/METADATA
dead_simple_framework-1.3.9.dist-info/WHEEL
dead_simple_framework-1.3.9.dist-info/top_level.txt
dead_simple_framework-1.3.9.dist-info/RECORD
