Metadata-Version: 2.1
Name: dead-simple-framework
Version: 1.3.9
Summary: RESTful Flask framework with builtin MongoDB, Redis, Celery, Sentry and Slack integrations
Home-page: https://github.com/Topazoo/dead_simple_framework
Author: Peter Swanson
Author-email: pswanson@ucdavis.edu
License: MIT
Requires-Python: >=3.5
Requires-Dist: flask
Requires-Dist: pymongo
Requires-Dist: celery
Requires-Dist: flask-cors
Requires-Dist: requests
Requires-Dist: redis
Requires-Dist: eventlet
Requires-Dist: pyOpenSSL
Requires-Dist: Flask-JWT-Extended
Requires-Dist: passlib
Requires-Dist: jsonschema
Requires-Dist: sentry-sdk[flask]
Requires-Dist: slack-sdk
Requires-Dist: Flask-PyMongo
